panorma/__init__.py
panorma/exceptions.py
panorma/fields.py
panorma/frames.py
panorma-0.1.1.dist-info/METADATA
panorma-0.1.1.dist-info/WHEEL
panorma-0.1.1.dist-info/RECORD
